<?xml version="1.0" encoding="UTF-8"?>
<PathOfBuilding>
	<Build level="100" targetVersion="3_0" pantheonMajorGod="Lunaris" bandit="None" className="Witch" ascendClassName="Necromancer" characterLevelAutoMode="false" mainSocketGroup="1" viewMode="TREE" pantheonMinorGod="Ryslatha">
		<Spectre id="Metadata/Monsters/LeagueAzmeri/SpecialCorpses/TurtleHigh"/>
		<Spectre id="Metadata/Monsters/LeagueAzmeri/SpecialCorpses/VikingHigh"/>
		<Spectre id="Metadata/Monsters/LeagueAzmeri/SpecialCorpses/TigerHigh"/>
		<PlayerStat stat="AverageDamage" value="1390.521941424"/>
		<PlayerStat stat="AverageBurstDamage" value="1390.521941424"/>
		<PlayerStat stat="Speed" value="0.79744816586922"/>
		<PlayerStat stat="PreEffectiveCritChance" value="8"/>
		<PlayerStat stat="CritChance" value="5.04"/>
		<PlayerStat stat="CritMultiplier" value="1.5"/>
		<PlayerStat stat="HitChance" value="63"/>
		<PlayerStat stat="TotalDPS" value="1108.8691717895"/>
		<PlayerStat stat="TotalDot" value="0"/>
		<PlayerStat stat="WithBleedDPS" value="1108.8691717895"/>
		<PlayerStat stat="WithIgniteDPS" value="1108.8691717895"/>
		<PlayerStat stat="WithPoisonDPS" value="1108.8691717895"/>
		<PlayerStat stat="TotalDotDPS" value="0"/>
		<PlayerStat stat="CullingDPS" value="0"/>
		<PlayerStat stat="ReservationDPS" value="0"/>
		<PlayerStat stat="CombinedDPS" value="1108.8691717895"/>
		<PlayerStat stat="Cooldown" value="1.254"/>
		<PlayerStat stat="ManaCost" value="0"/>
		<PlayerStat stat="ManaPercentCost" value="0"/>
		<PlayerStat stat="ManaPerSecondCost" value="0"/>
		<PlayerStat stat="ManaPercentPerSecondCost" value="0"/>
		<PlayerStat stat="LifeCost" value="85"/>
		<PlayerStat stat="LifePercentCost" value="0"/>
		<PlayerStat stat="LifePerSecondCost" value="67.783094098884"/>
		<PlayerStat stat="LifePercentPerSecondCost" value="0"/>
		<PlayerStat stat="ESCost" value="0"/>
		<PlayerStat stat="ESPerSecondCost" value="0"/>
		<PlayerStat stat="ESPercentPerSecondCost" value="0"/>
		<PlayerStat stat="RageCost" value="0"/>
		<PlayerStat stat="SoulCost" value="0"/>
		<PlayerStat stat="Str" value="54"/>
		<PlayerStat stat="Dex" value="24"/>
		<PlayerStat stat="Int" value="52"/>
		<PlayerStat stat="Devotion" value="0"/>
		<PlayerStat stat="TotalEHP" value="171991.66096111"/>
		<PlayerStat stat="PhysicalMaximumHitTaken" value="35869"/>
		<PlayerStat stat="LightningMaximumHitTaken" value="144492"/>
		<PlayerStat stat="FireMaximumHitTaken" value="144492"/>
		<PlayerStat stat="ColdMaximumHitTaken" value="144492"/>
		<PlayerStat stat="ChaosMaximumHitTaken" value="58345"/>
		<PlayerStat stat="MainHandAccuracy" value="976"/>
		<PlayerStat stat="Life" value="7532"/>
		<PlayerStat stat="Spec:LifeInc" value="125"/>
		<PlayerStat stat="LifeUnreserved" value="7337"/>
		<PlayerStat stat="LifeRecoverable" value="7337"/>
		<PlayerStat stat="LifeUnreservedPercent" value="97.411046202868"/>
		<PlayerStat stat="LifeRegenRecovery" value="862.2"/>
		<PlayerStat stat="LifeLeechGainRate" value="0"/>
		<PlayerStat stat="Mana" value="0"/>
		<PlayerStat stat="Spec:ManaInc" value="0"/>
		<PlayerStat stat="ManaRegenRecovery" value="0"/>
		<PlayerStat stat="ManaLeechGainRate" value="0"/>
		<PlayerStat stat="EnergyShield" value="0"/>
		<PlayerStat stat="EnergyShieldRecoveryCap" value="0"/>
		<PlayerStat stat="Spec:EnergyShieldInc" value="10"/>
		<PlayerStat stat="EnergyShieldRegenRecovery" value="0"/>
		<PlayerStat stat="EnergyShieldLeechGainRate" value="0"/>
		<PlayerStat stat="Ward" value="0"/>
		<PlayerStat stat="RageRegenRecovery" value="0"/>
		<PlayerStat stat="Evasion" value="7389"/>
		<PlayerStat stat="Spec:EvasionInc" value="66"/>
		<PlayerStat stat="MeleeEvadeChance" value="46"/>
		<PlayerStat stat="ProjectileEvadeChance" value="46"/>
		<PlayerStat stat="Armour" value="25509"/>
		<PlayerStat stat="Spec:ArmourInc" value="230"/>
		<PlayerStat stat="PhysicalDamageReduction" value="90"/>
		<PlayerStat stat="EffectiveBlockChance" value="0"/>
		<PlayerStat stat="EffectiveSpellBlockChance" value="0"/>
		<PlayerStat stat="AttackDodgeChance" value="0"/>
		<PlayerStat stat="SpellDodgeChance" value="0"/>
		<PlayerStat stat="EffectiveSpellSuppressionChance" value="100"/>
		<PlayerStat stat="FireResist" value="90"/>
		<PlayerStat stat="FireResistOverCap" value="14"/>
		<PlayerStat stat="ColdResist" value="90"/>
		<PlayerStat stat="ColdResistOverCap" value="15"/>
		<PlayerStat stat="LightningResist" value="90"/>
		<PlayerStat stat="LightningResistOverCap" value="12"/>
		<PlayerStat stat="ChaosResist" value="77"/>
		<PlayerStat stat="ChaosResistOverCap" value="3"/>
		<PlayerStat stat="EffectiveMovementSpeedMod" value="1.6905"/>
		<PlayerStat stat="FullDPS" value="53777441.251912"/>
		<PlayerStat stat="FullDotDPS" value="35791394"/>
		<FullDPSSkill skillPart="" source="" stat="Full Poison DPS" value="35791394"/>
		<FullDPSSkill skillPart="Clone: Rain of Arrow" source="" stat="9x Mirror Arrow of Bombarding Clones" value="12598323.304175"/>
		<FullDPSSkill skillPart="" source="" stat="Full Culling DPS" value="5377744.1251912"/>
		<FullDPSSkill skillPart="Rain of Arrow" source="" stat="9x Mirror Arrow of Bombarding Clones" value="9979.8225461053"/>
		<PlayerStat stat="PowerCharges" value="0"/>
		<PlayerStat stat="PowerChargesMax" value="3"/>
		<PlayerStat stat="FrenzyCharges" value="0"/>
		<PlayerStat stat="FrenzyChargesMax" value="3"/>
		<PlayerStat stat="EnduranceCharges" value="6"/>
		<PlayerStat stat="EnduranceChargesMax" value="6"/>
		<MinionStat stat="AverageDamage" value="260556.4925292"/>
		<MinionStat stat="Speed" value="5.3724"/>
		<MinionStat stat="Speed" value="5.3724"/>
		<MinionStat stat="TotalDPS" value="1399813.7004639"/>
		<MinionStat stat="TotalDot" value="0"/>
		<MinionStat stat="WithBleedDPS" value="1399813.7004639"/>
		<MinionStat stat="WithIgniteDPS" value="1399813.7004639"/>
		<MinionStat stat="PoisonDPS" value="8663983.2298314"/>
		<MinionStat stat="PoisonDamage" value="1612683.9456912"/>
		<MinionStat stat="WithPoisonDPS" value="10063796.930295"/>
		<MinionStat stat="TotalDotDPS" value="8663983.2298314"/>
		<MinionStat stat="CullingDPS" value="1118199.6589217"/>
		<MinionStat stat="ReservationDPS" value="0"/>
		<MinionStat stat="CombinedDPS" value="11181996.589217"/>
		<MinionStat stat="Life" value="10382"/>
		<MinionStat stat="LifeRegenRecovery" value="103.8"/>
		<MinionStat stat="LifeLeechGainRate" value="0"/>
		<MinionStat stat="EnergyShield" value="4163"/>
		<MinionStat stat="EnergyShieldRegenRecovery" value="0"/>
		<MinionStat stat="EnergyShieldLeechGainRate" value="0"/>
		<TimelessData devotionVariant2="1" searchListFallback="" searchList="" socketFilterDistance="0" devotionVariant1="1"/>
	</Build>
	<Import importLink="https://pobb.in/pob/92HvID3C0BBj" lastAccountHash="432c47bf84f6568f818db531ad4fa4ed2bbc156a" lastRealm="PC" lastCharacterHash="432c47bf84f6568f818db531ad4fa4ed2bbc156a" exportParty="false"/>
	<Party destination="All" ShowAdvanceTools="false" append="false"/>
	<Tree activeSpec="1">
		<Spec masteryEffects="{50757,57074},{12382,34242},{48290,58106},{25349,59634},{64406,7137}" ascendClassId="3" nodes="7388,10829,54447,23027,36634,65697,6289,26725,11497,39818,65705,34171,32091,49254,39085,34400,26196,49080,33287,65760,65698,37569,50422,57279,48287,55646,60791,29353,13231,930,65699,36542,11730,63723,53118,65707,15522,57264,46519,26712,60547,43133,25989,60031,16167,35503,44908,44169,44202,25349,14603,60398,42009,60472,34483,23185,50757,41472,65701,13714,55190,8930,28330,36915,50862,14930,46910,54267,61471,62429,45341,65702,43689,31875,55485,42041,26298,30380,3644,5233,10532,5408,34880,65034,36949,54159,59928,65706,31683,65703,65762,48290,35288,63282,36881,1203,18402,12382,33631,10031,11490,44103,23756,42668,28475,7399,37326,50570,13009,4397,48109,10904,56855,2491,65696,30733,64406,62319,26866,33740,18901,2913,17735,46578,55676,36687,27308,238,65153,15405,19144,49178,6712" secondaryAscendClassId="nil" treeVersion="3_25" classId="3">
			<URL>
				https://www.pathofexile.com/passive-skill-tree/AAAABgMDdxzcKk1Z848aGJFoZSzpm4qFe31bwGaYrYZgZlS_uIIHksHE9t-_vJ_ZXnKpM68Doo6-LdL4689-PKLfsLW3aFjsg6h9ZYXqfz8niq-vbKyJrKpjBTkL6-6kGew4hrNakcZFogA1kteWIuJuqpAzxq46Urc-0_vwH_PdsR2qqXyD2L2kOWa6dqwOPBRxKSQVIIhA_gqQVdOP6hh7w7yiidj3MpARBLNH4jBeg18nLyzirEdczKasbzsc55HOxYoy0REtu-0qmN4XCbt4DfuW829o8oPMSdULYUVHtfLZfI9PaqwA7v6BPC1KyMAaGjgMAKEAqQDgAKIAowCrAKUApgCqAKcA4gCgBejyYwXe8sZF4vq8ooXCMF4b4fuW
			</URL>
			<Sockets>
				<Socket nodeId="10532" itemId="12"/>
				<Socket nodeId="36634" itemId="10"/>
				<Socket nodeId="34483" itemId="14"/>
				<Socket nodeId="26725" itemId="1"/>
				<Socket nodeId="55190" itemId="4"/>
				<Socket nodeId="44169" itemId="6"/>
				<Socket nodeId="46519" itemId="3"/>
				<Socket nodeId="33631" itemId="5"/>
				<Socket nodeId="31683" itemId="8"/>
				<Socket nodeId="23756" itemId="7"/>
				<Socket nodeId="28475" itemId="11"/>
				<Socket nodeId="26196" itemId="13"/>
				<Socket nodeId="49080" itemId="2"/>
				<Socket nodeId="2491" itemId="9"/>
			</Sockets>
			<Overrides>
				<Override dn="Tattoo of the Arohongui Moonwarden" icon="Art/2DArt/SkillIcons/passives/ColdResistNode.png" nodeId="13009" activeEffectImage="Art/2DArt/UIImages/InGame/AncestralTrial/PassiveTreeTattoos/ArohonguiTribePassiveBG.png">
					+6% to Cold Resistance
				</Override>
				<Override dn="Tattoo of the Rongokurai Warrior" icon="Art/2DArt/SkillIcons/passives/dmgreduction.png" nodeId="50570" activeEffectImage="Art/2DArt/UIImages/InGame/AncestralTrial/PassiveTreeTattoos/RongokuraiTribePassiveBG.png">
					6% increased Armour
				</Override>
				<Override dn="Tattoo of the Rongokurai Warrior" icon="Art/2DArt/SkillIcons/passives/dmgreduction.png" nodeId="3644" activeEffectImage="Art/2DArt/UIImages/InGame/AncestralTrial/PassiveTreeTattoos/RongokuraiTribePassiveBG.png">
					6% increased Armour
				</Override>
				<Override dn="Tattoo of the Arohongui Moonwarden" icon="Art/2DArt/SkillIcons/passives/ColdResistNode.png" nodeId="10829" activeEffectImage="Art/2DArt/UIImages/InGame/AncestralTrial/PassiveTreeTattoos/ArohonguiTribePassiveBG.png">
					+6% to Cold Resistance
				</Override>
				<Override dn="Tattoo of the Ngamahu Firewalker" icon="Art/2DArt/SkillIcons/passives/FireResistNode.png" nodeId="34400" activeEffectImage="Art/2DArt/UIImages/InGame/AncestralTrial/PassiveTreeTattoos/NgamahuTribePassiveBG.png">
					+6% to Fire Resistance
				</Override>
				<Override dn="Tattoo of the Arohongui Moonwarden" icon="Art/2DArt/SkillIcons/passives/ColdResistNode.png" nodeId="16167" activeEffectImage="Art/2DArt/UIImages/InGame/AncestralTrial/PassiveTreeTattoos/ArohonguiTribePassiveBG.png">
					+6% to Cold Resistance
				</Override>
				<Override dn="Tattoo of the Rongokurai Warrior" icon="Art/2DArt/SkillIcons/passives/dmgreduction.png" nodeId="46910" activeEffectImage="Art/2DArt/UIImages/InGame/AncestralTrial/PassiveTreeTattoos/RongokuraiTribePassiveBG.png">
					6% increased Armour
				</Override>
				<Override dn="Tattoo of the Rongokurai Warrior" icon="Art/2DArt/SkillIcons/passives/dmgreduction.png" nodeId="60472" activeEffectImage="Art/2DArt/UIImages/InGame/AncestralTrial/PassiveTreeTattoos/RongokuraiTribePassiveBG.png">
					6% increased Armour
				</Override>
				<Override dn="Tattoo of the Ngamahu Firewalker" icon="Art/2DArt/SkillIcons/passives/FireResistNode.png" nodeId="14930" activeEffectImage="Art/2DArt/UIImages/InGame/AncestralTrial/PassiveTreeTattoos/NgamahuTribePassiveBG.png">
					+6% to Fire Resistance
				</Override>
				<Override dn="Tattoo of the Rongokurai Warrior" icon="Art/2DArt/SkillIcons/passives/dmgreduction.png" nodeId="23027" activeEffectImage="Art/2DArt/UIImages/InGame/AncestralTrial/PassiveTreeTattoos/RongokuraiTribePassiveBG.png">
					6% increased Armour
				</Override>
				<Override dn="Tattoo of the Hinekora Warmonger" icon="Art/2DArt/SkillIcons/passives/minionlife.png" nodeId="4397" activeEffectImage="Art/2DArt/UIImages/InGame/AncestralTrial/PassiveTreeTattoos/HinekoraTribePassiveBG.png">
					Minions have 5% increased maximum Life
				</Override>
				<Override dn="Tattoo of the Rongokurai Warrior" icon="Art/2DArt/SkillIcons/passives/dmgreduction.png" nodeId="50862" activeEffectImage="Art/2DArt/UIImages/InGame/AncestralTrial/PassiveTreeTattoos/RongokuraiTribePassiveBG.png">
					6% increased Armour
				</Override>
				<Override dn="Tattoo of the Ngamahu Firewalker" icon="Art/2DArt/SkillIcons/passives/FireResistNode.png" nodeId="46578" activeEffectImage="Art/2DArt/UIImages/InGame/AncestralTrial/PassiveTreeTattoos/NgamahuTribePassiveBG.png">
					+6% to Fire Resistance
				</Override>
				<Override dn="Tattoo of the Rongokurai Warrior" icon="Art/2DArt/SkillIcons/passives/dmgreduction.png" nodeId="15405" activeEffectImage="Art/2DArt/UIImages/InGame/AncestralTrial/PassiveTreeTattoos/RongokuraiTribePassiveBG.png">
					6% increased Armour
				</Override>
				<Override dn="Tattoo of the Rongokurai Warrior" icon="Art/2DArt/SkillIcons/passives/dmgreduction.png" nodeId="30733" activeEffectImage="Art/2DArt/UIImages/InGame/AncestralTrial/PassiveTreeTattoos/RongokuraiTribePassiveBG.png">
					6% increased Armour
				</Override>
				<Override dn="Tattoo of the Ngamahu Firewalker" icon="Art/2DArt/SkillIcons/passives/FireResistNode.png" nodeId="44908" activeEffectImage="Art/2DArt/UIImages/InGame/AncestralTrial/PassiveTreeTattoos/NgamahuTribePassiveBG.png">
					+6% to Fire Resistance
				</Override>
				<Override dn="Tattoo of the Rongokurai Warrior" icon="Art/2DArt/SkillIcons/passives/dmgreduction.png" nodeId="63282" activeEffectImage="Art/2DArt/UIImages/InGame/AncestralTrial/PassiveTreeTattoos/RongokuraiTribePassiveBG.png">
					6% increased Armour
				</Override>
				<Override dn="Tattoo of the Hinekora Warmonger" icon="Art/2DArt/SkillIcons/passives/minionlife.png" nodeId="36542" activeEffectImage="Art/2DArt/UIImages/InGame/AncestralTrial/PassiveTreeTattoos/HinekoraTribePassiveBG.png">
					Minions have 5% increased maximum Life
				</Override>
				<Override dn="Tattoo of the Rongokurai Warrior" icon="Art/2DArt/SkillIcons/passives/dmgreduction.png" nodeId="44202" activeEffectImage="Art/2DArt/UIImages/InGame/AncestralTrial/PassiveTreeTattoos/RongokuraiTribePassiveBG.png">
					6% increased Armour
				</Override>
				<Override dn="Tattoo of the Rongokurai Warrior" icon="Art/2DArt/SkillIcons/passives/dmgreduction.png" nodeId="59928" activeEffectImage="Art/2DArt/UIImages/InGame/AncestralTrial/PassiveTreeTattoos/RongokuraiTribePassiveBG.png">
					6% increased Armour
				</Override>
				<Override dn="Tattoo of the Hinekora Warmonger" icon="Art/2DArt/SkillIcons/passives/minionlife.png" nodeId="37569" activeEffectImage="Art/2DArt/UIImages/InGame/AncestralTrial/PassiveTreeTattoos/HinekoraTribePassiveBG.png">
					Minions have 5% increased maximum Life
				</Override>
				<Override dn="Tattoo of the Valako Stormrider" icon="Art/2DArt/SkillIcons/passives/LightningResistNode.png" nodeId="17735" activeEffectImage="Art/2DArt/UIImages/InGame/AncestralTrial/PassiveTreeTattoos/ValakoTribePassiveBG.png">
					+6% to Lightning Resistance
				</Override>
				<Override dn="Tattoo of the Rongokurai Warrior" icon="Art/2DArt/SkillIcons/passives/dmgreduction.png" nodeId="33740" activeEffectImage="Art/2DArt/UIImages/InGame/AncestralTrial/PassiveTreeTattoos/RongokuraiTribePassiveBG.png">
					6% increased Armour
				</Override>
				<Override dn="Tattoo of the Rongokurai Warrior" icon="Art/2DArt/SkillIcons/passives/dmgreduction.png" nodeId="50422" activeEffectImage="Art/2DArt/UIImages/InGame/AncestralTrial/PassiveTreeTattoos/RongokuraiTribePassiveBG.png">
					6% increased Armour
				</Override>
				<Override dn="Tattoo of the Rongokurai Warrior" icon="Art/2DArt/SkillIcons/passives/dmgreduction.png" nodeId="34171" activeEffectImage="Art/2DArt/UIImages/InGame/AncestralTrial/PassiveTreeTattoos/RongokuraiTribePassiveBG.png">
					6% increased Armour
				</Override>
				<Override dn="Tattoo of the Rongokurai Warrior" icon="Art/2DArt/SkillIcons/passives/dmgreduction.png" nodeId="63723" activeEffectImage="Art/2DArt/UIImages/InGame/AncestralTrial/PassiveTreeTattoos/RongokuraiTribePassiveBG.png">
					6% increased Armour
				</Override>
				<Override dn="Tattoo of the Rongokurai Warrior" icon="Art/2DArt/SkillIcons/passives/dmgreduction.png" nodeId="5233" activeEffectImage="Art/2DArt/UIImages/InGame/AncestralTrial/PassiveTreeTattoos/RongokuraiTribePassiveBG.png">
					6% increased Armour
				</Override>
				<Override dn="Tattoo of the Ngamahu Firewalker" icon="Art/2DArt/SkillIcons/passives/FireResistNode.png" nodeId="28330" activeEffectImage="Art/2DArt/UIImages/InGame/AncestralTrial/PassiveTreeTattoos/NgamahuTribePassiveBG.png">
					+6% to Fire Resistance
				</Override>
				<Override dn="Tattoo of the Hinekora Warmonger" icon="Art/2DArt/SkillIcons/passives/minionlife.png" nodeId="7388" activeEffectImage="Art/2DArt/UIImages/InGame/AncestralTrial/PassiveTreeTattoos/HinekoraTribePassiveBG.png">
					Minions have 5% increased maximum Life
				</Override>
				<Override dn="Tattoo of the Rongokurai Warrior" icon="Art/2DArt/SkillIcons/passives/dmgreduction.png" nodeId="29353" activeEffectImage="Art/2DArt/UIImages/InGame/AncestralTrial/PassiveTreeTattoos/RongokuraiTribePassiveBG.png">
					6% increased Armour
				</Override>
				<Override dn="Tattoo of the Hinekora Warmonger" icon="Art/2DArt/SkillIcons/passives/minionlife.png" nodeId="60398" activeEffectImage="Art/2DArt/UIImages/InGame/AncestralTrial/PassiveTreeTattoos/HinekoraTribePassiveBG.png">
					Minions have 5% increased maximum Life
				</Override>
				<Override dn="Tattoo of the Rongokurai Warrior" icon="Art/2DArt/SkillIcons/passives/dmgreduction.png" nodeId="49178" activeEffectImage="Art/2DArt/UIImages/InGame/AncestralTrial/PassiveTreeTattoos/RongokuraiTribePassiveBG.png">
					6% increased Armour
				</Override>
			</Overrides>
		</Spec>
	</Tree>
	<Notes>
		
	</Notes>
	<Skills sortGemsByDPSField="CombinedDPS" activeSkillSet="1" sortGemsByDPS="true" defaultGemQuality="0" defaultGemLevel="normalMaximum" showSupportGemTypes="ALL" showAltQualityGems="false">
		<SkillSet id="1">
			<Skill mainActiveSkillCalcs="1" includeInFullDPS="true" label="^5Bow - Clones (Predator for single target)" enabled="true" slot="Weapon 1" mainActiveSkill="1">
				<Gem enableGlobal2="false" skillMinionSkillCalcs="1" skillMinionCalcs="ArrowCloneRoA" level="21" gemId="Metadata/Items/Gems/SkillGemMirrorArrow" variantId="MirrorArrowAltX" skillId="MirrorArrowAltX" skillMinionSkill="1" quality="20" qualityId="Default" enableGlobal1="true" enabled="true" count="9" nameSpec="Mirror Arrow of Bombarding Clones" skillMinion="ArrowCloneRoA"/>
				<Gem enableGlobal2="false" level="6" gemId="Metadata/Items/Gems/SupportGemViciousProjectilesPlus" variantId="SupportAwakenedViciousProjectiles" skillId="SupportAwakenedViciousProjectiles" quality="20" qualityId="Default" enableGlobal1="true" enabled="true" count="1" nameSpec="Awakened Vicious Projectiles"/>
				<Gem enableGlobal2="false" level="6" gemId="Metadata/Items/Gems/SupportGemMinionDamagePlus" variantId="SupportAwakenedMinionDamage" skillId="SupportAwakenedMinionDamage" quality="20" qualityId="Default" enableGlobal1="true" enabled="true" count="1" nameSpec="Awakened Minion Damage"/>
				<Gem enableGlobal2="false" level="6" gemId="Metadata/Items/Gems/SupportGemUnboundAilmentsPlus" variantId="SupportAwakenedUnboundAilments" skillId="SupportAwakenedUnboundAilments" quality="20" qualityId="Default" enableGlobal1="true" enabled="true" count="1" nameSpec="Awakened Unbound Ailments"/>
				<Gem enableGlobal2="false" level="6" gemId="Metadata/Items/Gems/SupportGemVoidManipulationPlus" variantId="SupportAwakenedVoidManipulation" skillId="SupportAwakenedVoidManipulation" quality="20" qualityId="Default" enableGlobal1="true" enabled="true" count="1" nameSpec="Awakened Void Manipulation"/>
				<Gem enableGlobal2="true" level="21" gemId="Metadata/Items/Gems/SupportGemDeathmark" variantId="SupportPredator" skillId="SupportPredator" quality="20" qualityId="Default" enableGlobal1="true" enabled="true" count="1" nameSpec="Predator"/>
				<Gem enableGlobal2="true" skillMinionSkillCalcs="1" level="6" gemId="Metadata/Items/Gems/SupportGemAddedChaosDamagePlus" variantId="SupportAwakenedAddedChaosDamage" skillId="SupportAwakenedAddedChaosDamage" skillMinionSkill="1" skillMinionItemSet="1" quality="20" qualityId="Default" enableGlobal1="true" enabled="false" count="1" nameSpec="Awakened Added Chaos Damage" skillMinion="AnimatedWeapon"/>
			</Skill>
			<Skill mainActiveSkillCalcs="1" includeInFullDPS="false" label="^4Body - Support Minions" enabled="true" slot="Body Armour" mainActiveSkill="1">
				<Gem enableGlobal2="false" skillMinionSkillCalcs="1" level="21" gemId="Metadata/Items/Gems/SkillGemRaiseSpectre" variantId="RaiseSpectre" skillId="RaiseSpectre" skillMinionSkill="1" quality="20" qualityId="Default" enableGlobal1="true" enabled="true" count="1" nameSpec="Raise Spectre" skillMinion="Metadata/Monsters/LeagueAzmeri/SpecialCorpses/TurtleHigh"/>
				<Gem enableGlobal2="false" level="4" gemId="Metadata/Items/Gems/SupportGemAdditionalLevel" variantId="SupportEmpower" skillId="SupportEmpower" quality="20" qualityId="Default" enableGlobal1="true" enabled="true" count="1" nameSpec="Empower"/>
				<Gem enableGlobal2="false" level="20" gemId="Metadata/Items/Gems/SupportGemMinionLife" variantId="SupportMinionLife" skillId="SupportMinionLife" quality="20" qualityId="Default" enableGlobal1="true" enabled="true" count="1" nameSpec="Minion Life"/>
				<Gem enableGlobal2="false" level="20" gemId="Metadata/Items/Gems/SupportGemFeedingFrenzy" variantId="SupportFeedingFrenzy" skillId="SupportFeedingFrenzy" quality="20" qualityId="Default" enableGlobal1="true" enabled="true" count="1" nameSpec="Feeding Frenzy"/>
				<Gem enableGlobal2="false" skillMinionSkillCalcs="1" level="21" gemId="Metadata/Items/Gems/SkillGemAnimateArmour" variantId="AnimateGuardian" skillId="AnimateGuardian" skillMinionSkill="1" skillMinionItemSet="2" quality="20" qualityId="Default" enableGlobal1="true" enabled="true" count="1" nameSpec="Animate Guardian" skillMinion="AnimatedArmour"/>
				<Gem enableGlobal2="false" level="21" gemId="Metadata/Items/Gems/SupportGemMeatShield" variantId="SupportMeatShield" skillId="SupportMeatShield" quality="20" qualityId="Default" enableGlobal1="true" enabled="true" count="1" nameSpec="Meat Shield"/>
			</Skill>
			<Skill mainActiveSkillCalcs="1" includeInFullDPS="false" label="" enabled="true" slot="Helmet" mainActiveSkill="1">
				<Gem enableGlobal2="false" level="20" gemId="Metadata/Items/Gems/SkillGemAutomation" variantId="Automation" skillId="Automation" quality="20" qualityId="Default" enableGlobal1="true" enabled="true" count="1" nameSpec="Automation"/>
				<Gem enableGlobal2="false" level="1" gemId="Metadata/Items/Gems/SkillGemConvocationNew" variantId="Convocation" skillId="Convocation" quality="20" qualityId="Default" enableGlobal1="true" enabled="true" count="1" nameSpec="Convocation"/>
			</Skill>
			<Skill mainActiveSkillCalcs="1" includeInFullDPS="false" label="" enabled="true" slot="Helmet" mainActiveSkill="1">
				<Gem enableGlobal2="false" level="3" gemId="Metadata/Items/Gems/SupportGemCastOnDamageTaken" variantId="SupportCastWhenDamageTaken" skillId="SupportCastWhenDamageTaken" quality="20" qualityId="Default" enableGlobal1="true" enabled="true" count="1" nameSpec="Cast when Damage Taken"/>
				<Gem enableGlobal2="false" level="8" gemId="Metadata/Items/Gems/SkillGemVaalMoltenShell" variantId="VaalMoltenShell" skillId="VaalMoltenShell" quality="20" qualityId="Default" enableGlobal1="false" enabled="true" count="1" nameSpec="Vaal Molten Shell"/>
			</Skill>
			<Skill mainActiveSkillCalcs="1" includeInFullDPS="false" label="" enabled="true" slot="Boots" mainActiveSkill="1">
				<Gem enableGlobal2="false" level="21" gemId="Metadata/Items/Gems/SkillGemDamageOverTimeAura" variantId="Malevolence" skillId="Malevolence" quality="20" qualityId="Default" enableGlobal1="true" enabled="true" count="1" nameSpec="Malevolence"/>
				<Gem enableGlobal2="false" level="21" gemId="Metadata/Items/Gems/SkillGemVulnerability" variantId="Despair" skillId="Despair" quality="20" qualityId="Default" enableGlobal1="true" enabled="true" count="1" nameSpec="Despair"/>
				<Gem enableGlobal2="false" level="21" gemId="Metadata/Items/Gems/SupportGemEternalBlessing" variantId="SupportEternalBlessing" skillId="SupportEternalBlessing" quality="20" qualityId="Default" enableGlobal1="true" enabled="true" count="1" nameSpec="Eternal Blessing"/>
				<Gem enableGlobal2="false" level="6" gemId="Metadata/Items/Gems/SupportGemGenerosityPlus" variantId="SupportAwakenedGenerosity" skillId="SupportAwakenedGenerosity" quality="20" qualityId="Default" enableGlobal1="true" enabled="true" count="1" nameSpec="Awakened Generosity"/>
			</Skill>
			<Skill mainActiveSkillCalcs="1" includeInFullDPS="false" label="" enabled="true" slot="Gloves" mainActiveSkill="1">
				<Gem enableGlobal2="false" skillMinionSkillCalcs="1" level="21" gemId="Metadata/Items/Gems/SkillGemSummonCarrionGolem" variantId="SummonCarrionGolem" skillId="SummonCarrionGolem" skillMinionSkill="1" quality="20" qualityId="Default" enableGlobal1="true" enabled="true" count="1" nameSpec="Summon Carrion Golem" skillMinion="SummonedCarrionGolem"/>
			</Skill>
			<Skill mainActiveSkillCalcs="1" includeInFullDPS="false" label="" enabled="true" slot="Gloves" mainActiveSkill="1">
				<Gem enableGlobal2="false" level="20" gemId="Metadata/Items/Gems/SkillGemFrostblink" variantId="Frostblink" skillId="Frostblink" quality="20" qualityId="Default" enableGlobal1="true" enabled="true" count="1" nameSpec="Frostblink"/>
			</Skill>
			<Skill mainActiveSkillCalcs="1" includeInFullDPS="false" label="" enabled="true" slot="Gloves" mainActiveSkill="1">
				<Gem enableGlobal2="false" level="1" gemId="Metadata/Items/Gems/SkillGemDesecrate" variantId="Desecrate" skillId="Desecrate" quality="20" qualityId="Default" enableGlobal1="true" enabled="true" count="1" nameSpec="Desecrate"/>
			</Skill>
			<Skill mainActiveSkillCalcs="1" includeInFullDPS="false" label="" enabled="true" slot="Gloves" mainActiveSkill="1">
				<Gem enableGlobal2="true" level="21" gemId="Metadata/Items/Gems/SkillGemPrecision" variantId="Precision" skillId="Precision" quality="20" qualityId="Default" enableGlobal1="true" enabled="true" count="1" nameSpec="Precision"/>
			</Skill>
			<Skill mainActiveSkillCalcs="1" includeInFullDPS="false" label="^6AG - Curse" enabled="true" mainActiveSkill="1">
				<Gem enableGlobal2="true" level="1" gemId="Metadata/Items/Gems/SkillGemTemporalChains" variantId="TemporalChains" skillId="TemporalChains" quality="20" qualityId="Default" enableGlobal1="true" enabled="true" count="1" nameSpec="Temporal Chains"/>
			</Skill>
		</SkillSet>
	</Skills>
	<Calcs>
		<Input name="showMinion" boolean="true"/>
		<Input name="skill_number" number="1"/>
		<Input name="misc_buffMode" string="EFFECTIVE"/>
		<Section subsection="ViewSkillDetails" collapsed="false" id="SkillSelect"/>
		<Section subsection="SkillHitDamage" collapsed="false" id="HitDamage"/>
		<Section subsection="ExertingWarcries" collapsed="false" id="Warcries"/>
		<Section subsection="SkillDamageoverTime" collapsed="false" id="Dot"/>
		<Section subsection="AttackCastRate" collapsed="false" id="Speed"/>
		<Section subsection="Crits" collapsed="false" id="Crit"/>
		<Section subsection="Impale" collapsed="false" id="Impale"/>
		<Section subsection="SkilltypespecificStats" collapsed="false" id="SkillTypeStats"/>
		<Section subsection="Accuracy" collapsed="false" id="HitChance"/>
		<Section subsection="Bleed" collapsed="false" id="Bleed"/>
		<Section subsection="Poison" collapsed="false" id="Poison"/>
		<Section subsection="Ignite" collapsed="false" id="Ignite"/>
		<Section subsection="Decay" collapsed="false" id="Decay"/>
		<Section subsection="LeechGainonHit" collapsed="false" id="LeechGain"/>
		<Section subsection="NonDamagingAilments" collapsed="false" id="EleAilments"/>
		<Section subsection="OtherEffects" collapsed="false" id="MiscEffects"/>
		<Section subsection="Attributes" collapsed="false" id="Attributes"/>
		<Section subsection="Life" collapsed="false" id="Life"/>
		<Section subsection="Mana" collapsed="false" id="Mana"/>
		<Section subsection="EnergyShield" collapsed="false" id="EnergyShield"/>
		<Section subsection="Ward" collapsed="false" id="Ward"/>
		<Section subsection="Resists" collapsed="false" id="Resist"/>
		<Section subsection="Armour" collapsed="false" id="Armour"/>
		<Section subsection="Evasion" collapsed="false" id="Evasion"/>
		<Section subsection="DamageAvoidance" collapsed="false" id="DamageAvoidance"/>
		<Section subsection="Block" collapsed="false" id="DamageAvoidance"/>
		<Section subsection="Dodge" collapsed="false" id="DamageAvoidance"/>
		<Section subsection="SpellSuppression" collapsed="false" id="DamageAvoidance"/>
		<Section subsection="Flasks" collapsed="false" id="Flasks"/>
		<Section subsection="UtilityFlasks" collapsed="true" id="Flasks"/>
		<Section subsection="LifeFlasks" collapsed="true" id="Flasks"/>
		<Section subsection="ManaFlasks" collapsed="true" id="Flasks"/>
		<Section subsection="Tinctures" collapsed="true" id="Flasks"/>
		<Section subsection="Rage" collapsed="true" id="Rage"/>
		<Section subsection="Charges" collapsed="true" id="Charges"/>
		<Section subsection="Endurance" collapsed="true" id="Charges"/>
		<Section subsection="Frenzy" collapsed="true" id="Charges"/>
		<Section subsection="Power" collapsed="true" id="Charges"/>
		<Section subsection="OtherDefences" collapsed="false" id="MiscDefences"/>
		<Section subsection="StunDuration" collapsed="false" id="MiscDefences"/>
		<Section subsection="OtherAvoidance" collapsed="true" id="MiscDefences"/>
		<Section subsection="OtherAilmentDefences" collapsed="true" id="MiscDefences"/>
		<Section subsection="DamageTaken" collapsed="false" id="DamageTaken"/>
		<Section subsection="DamagingHits" collapsed="false" id="DamageTaken"/>
		<Section subsection="EffectiveHealthPool" collapsed="false" id="DamageTaken"/>
		<Section subsection="MaximumHitTaken" collapsed="false" id="DamageTaken"/>
		<Section subsection="RecoupandHitTakenOverTime" collapsed="true" id="DamageTaken"/>
		<Section subsection="DotsandBuildDegens" collapsed="false" id="DamageTaken"/>
		<Section subsection="EnemyDegens" collapsed="true" id="DamageTaken"/>
	</Calcs>
	<TreeView searchStr="" zoomY="-73" zoomLevel="2" showStatDifferences="true" zoomX="-32.166666666667"/>
	<Items activeItemSet="1" showStatDifferences="true" useSecondWeaponSet="false">
		<Item id="1">
			Rarity: UNIQUE
Grand Spectrum
Crimson Jewel
Unique ID: 1924f21ef42714e6ee33415290cf5597fa508e89518796ac9cb74bc04de54f1a
Item Level: 80
Limited to: 3
Implicits: 1
24% reduced Ignite Duration on you
5% increased Maximum Life per Grand Spectrum
Corrupted
			<ModRange range="0.5" id="1"/>
			<ModRange range="0.5" id="2"/>
		</Item>
		<Item id="2">
			Rarity: MAGIC
Flaring Ghastly Eye Jewel of Venom
Unique ID: a1157cf23f94047e094ed5dae27cb041a4c450ee8c1d827da68237e810d2ba71
Item Level: 85
LevelReq: 66
Implicits: 1
Hits have 11% chance to ignore Enemy Physical Damage Reduction
Minions have 13% chance to Poison Enemies on Hit
Minions deal 24 to 36 additional Physical Damage
Split
Corrupted
			<ModRange range="0.5" id="1"/>
			<ModRange range="0.5" id="2"/>
			<ModRange range="0.5" id="3"/>
		</Item>
		<Item id="3">
			Rarity: MAGIC
Flaring Ghastly Eye Jewel of Venom
Unique ID: f05608e92e4f18207dad9cdafbf031665b52fc9ee6e643490e97a405fe5c404d
Item Level: 83
LevelReq: 66
Implicits: 0
Minions have 15% chance to Poison Enemies on Hit
Minions deal 25 to 33 additional Physical Damage
Corrupted
			<ModRange range="0.5" id="1"/>
			<ModRange range="0.5" id="2"/>
		</Item>
		<Item id="4">
			Rarity: RARE
Honour Wound
Large Cluster Jewel
Unique ID: f4aee0c38f27c14acb1027bd011449638e86e618ab6e337bdfcc37ced7432d35
Item Level: 85
LevelReq: 67
Implicits: 3
{crafted}Adds 12 Passive Skills
{crafted}2 Added Passive Skills are Jewel Sockets
{crafted}Added Small Passive Skills grant: Minions deal 10% increased Damage
Added Small Passive Skills also grant: +4% to all Elemental Resistances
Added Small Passive Skills also grant: +7 to Maximum Life
Added Small Passive Skills also grant: Minions have 3% increased Attack and Cast Speed
Added Small Passive Skills have 35% increased Effect
			<ModRange range="0.5" id="1"/>
			<ModRange range="0.5" id="2"/>
			<ModRange range="0.5" id="3"/>
			<ModRange range="0.5" id="4"/>
			<ModRange range="0.5" id="5"/>
			<ModRange range="0.5" id="6"/>
			<ModRange range="0.5" id="7"/>
		</Item>
		<Item id="5">
			Rarity: UNIQUE
Grand Spectrum
Crimson Jewel
Unique ID: 6c3d513f20169b0630bd1901f792f055163e2eb8d2f92590bec1c9e4b6dbcde5
Item Level: 75
Limited to: 3
Implicits: 0
+1 to Minimum Endurance Charges per Grand Spectrum
			<ModRange range="0.5" id="1"/>
		</Item>
		<Item id="6">
			Rarity: UNIQUE
The Adorned
Crimson Jewel
Unique ID: 4a1e05baf2c085c0c0a5c64d26df1ce5f6e25e6e7e3ea3eec53232d1cfa28aca
Item Level: 82
Limited to: 1
Implicits: 0
93% increased Effect of Jewel Socket Passive Skills containing Corrupted Magic Jewels
Corrupted
			<ModRange range="0.5" id="1"/>
		</Item>
		<Item id="7">
			Rarity: MAGIC
Flaring Ghastly Eye Jewel of Training
Unique ID: f8250bd5170c64e78644c622546bef44725615c0143252a77ed8ed7ac3a1ddf0
Item Level: 83
LevelReq: 66
Implicits: 1
Corrupted Blood cannot be inflicted on you
{fractured}Minions have 6% increased Attack Speed
{fractured}Minions have 6% increased Cast Speed
Minions deal 23 to 39 additional Physical Damage
Corrupted
			<ModRange range="0.5" id="1"/>
			<ModRange range="0.5" id="2"/>
			<ModRange range="0.5" id="3"/>
			<ModRange range="0.5" id="4"/>
		</Item>
		<Item id="8">
			Rarity: MAGIC
Flaring Ghastly Eye Jewel of Venom
Unique ID: 5778472e33e196344f26a88da5d78ae418eb7c788559b4fe61790d6c42624a35
Item Level: 85
LevelReq: 66
Implicits: 0
Minions have 14% chance to Poison Enemies on Hit
Minions deal 23 to 37 additional Physical Damage
Corrupted
			<ModRange range="0.5" id="1"/>
			<ModRange range="0.5" id="2"/>
		</Item>
		<Item id="9">
			Rarity: UNIQUE
Voices
Large Cluster Jewel
Unique ID: 205e721503f2abab4a5fe0363aaa22b92c0d7e5a95fb9f6fe40eb38b75ce9350
Item Level: 84
Implicits: 0
Adds 3 Jewel Socket Passive Skills
Adds 3 Small Passive Skills which grant nothing
Corrupted
			<ModRange range="0.5" id="1"/>
			<ModRange range="0.5" id="2"/>
		</Item>
		<Item id="10">
			Rarity: UNIQUE
Grand Spectrum
Crimson Jewel
Unique ID: 7315273709e982386574ad6d91d65c7de81faf90e63d2b557164792ec460746e
Item Level: 68
Limited to: 3
Implicits: 0
+1 to Minimum Endurance Charges per Grand Spectrum
			<ModRange range="0.5" id="1"/>
		</Item>
		<Item id="11">
			Rarity: UNIQUE
Rational Doctrine
Cobalt Jewel
Unique ID: 89dc940ef172089ba50dce48f409635b037ee486aa3b6774f07606fde4c8a456
Item Level: 87
Implicits: 3
5% increased Lightning Damage
Minions have 3% increased Attack Speed
Minions have +5% to all Elemental Resistances
You have Consecrated Ground around you while
stationary if Strength is your highest Attribute
25% chance to create Profane Ground on Critical
Strike if Intelligence is your highest Attribute
Effects of Consecrated Ground you create Linger for 4 seconds
Effects of Profane Ground you create Linger for 4 seconds
			<ModRange range="0.5" id="1"/>
			<ModRange range="0.5" id="2"/>
			<ModRange range="0.5" id="3"/>
			<ModRange range="0.5" id="4"/>
			<ModRange range="0.5" id="5"/>
		</Item>
		<Item id="12">
			Rarity: MAGIC
Flaring Ghastly Eye Jewel of Venom
Unique ID: eba3c652dabc334bdda3e7b1e7a6ba78356b00d4a25d3b6d725823c1be8cdb27
Item Level: 83
LevelReq: 66
Implicits: 1
Damage Penetrates 1% Cold Resistance
{fractured}Minions have 13% chance to Poison Enemies on Hit
Minions deal 25 to 35 additional Physical Damage
Corrupted
			<ModRange range="0.5" id="1"/>
			<ModRange range="0.5" id="2"/>
			<ModRange range="0.5" id="3"/>
		</Item>
		<Item id="13">
			Rarity: RELIC
Impossible Escape
Viridian Jewel
Unique ID: 1b3c29cb3a380ea3d5b88403f8ba53c07be3d3eb9a106b38a88d66975d5ba6de
Item Level: 84
Radius: Small
Limited to: 1
Implicits: 0
Passives in Radius of Imbalanced Guard can be Allocated
without being connected to your tree
Corrupted
			<ModRange range="0.5" id="1"/>
		</Item>
		<Item id="14">
			Rarity: UNIQUE
Elegant Hubris
Timeless Jewel
Unique ID: 1302b43a4359efc29fc6288a9b07d3da075aa1144a28cca4962ece1d36d7cae4
Item Level: 84
Radius: Large
Implicits: 0
Commissioned 68220 coins to commemorate Caspiro
Passives in radius are Conquered by the Eternal Empire
Historic
			<ModRange range="0.5" id="1"/>
			<ModRange range="0.5" id="2"/>
			<ModRange range="0.5" id="3"/>
		</Item>
		<Item id="15">
			Rarity: MAGIC
Seething Divine Life Flask
Unique ID: b17e0af13d8c40beb60148209ee90dc65805fd3f0e82a97937e984d245c5e1b2
Item Level: 72
Quality: 20
LevelReq: 60
Implicits: 1
{crafted}35% reduced Charges per use. -1% to this value when used
{fractured}66% reduced Amount Recovered
{fractured}Instant Recovery
			<ModRange range="0.5" id="1"/>
			<ModRange range="0.5" id="2"/>
			<ModRange range="0.5" id="3"/>
		</Item>
		<Item id="16">
			Rarity: RARE
Rage Halo
Haunted Bascinet
Armour: 977
ArmourBasePercentile: 1
Evasion: 977
EvasionBasePercentile: 1
Unique ID: 7086558a53134b36f5b67ea1c6a8f68feba9fa27361e274e53a385d32e17ae0a
Item Level: 84
Quality: 20
Sockets: B-B R-R
LevelReq: 84
Implicits: 2
7% of Physical Damage from Hits taken as Lightning Damage
Minions have 25% increased maximum Life
+8% chance to Suppress Spell Damage
99% increased Armour and Evasion
+143 to maximum Life
+2 to Level of all Minion Skill Gems
+30% to Chaos Resistance
{crafted}+15% to Fire and Chaos Resistances
			<ModRange range="0.5" id="1"/>
			<ModRange range="0.5" id="2"/>
			<ModRange range="0.5" id="3"/>
			<ModRange range="0.5" id="4"/>
			<ModRange range="0.5" id="5"/>
			<ModRange range="0.5" id="6"/>
			<ModRange range="0.5" id="7"/>
			<ModRange range="0.5" id="8"/>
		</Item>
		<Item id="17">
			Rarity: RARE
Morbid Iridescence
Ghastly Eye Jewel
Unique ID: cb965486f702dd55eabfaf3f213aadf677ec290437f1cea3f3e552a17de7e42e
Item Level: 84
LevelReq: 57
Implicits: 0
+25 to maximum Life
Minions deal 20% increased Damage if you&apos;ve used a Minion Skill Recently
+10% to Cold and Lightning Resistances
Minions have 5% increased Attack Speed
Minions have 5% increased Cast Speed
Minions deal 1 to 48 additional Lightning Damage
Minions deal 20 to 25 additional Physical Damage
Corrupted
			<ModRange range="0.5" id="1"/>
			<ModRange range="0.5" id="2"/>
			<ModRange range="0.5" id="3"/>
			<ModRange range="0.5" id="4"/>
			<ModRange range="0.5" id="5"/>
			<ModRange range="0.5" id="6"/>
			<ModRange range="0.5" id="7"/>
		</Item>
		<Item id="18">
			Rarity: RARE
Hollow Sight
Ghastly Eye Jewel
Unique ID: e59d365975e9bb35ab2d0a761167118120955462e480d9585d322757946d0667
Item Level: 83
LevelReq: 66
Implicits: 0
{fractured}50% chance to Avoid being Shocked
+22 to maximum Life
Minions have 6% increased Attack Speed
Minions have 4% increased Cast Speed
Minions deal 25 to 37 additional Physical Damage
			<ModRange range="0.5" id="1"/>
			<ModRange range="0.5" id="2"/>
			<ModRange range="0.5" id="3"/>
			<ModRange range="0.5" id="4"/>
			<ModRange range="0.5" id="5"/>
		</Item>
		<Item id="19">
			Rarity: UNIQUE
Darkness Enthroned
Stygian Vise
Unique ID: aa8d3a8ecc2b7f75a51e8df290982aa78b5eded822a1833d54932bf8192603bb
Item Level: 84
Sockets: A A
Implicits: 1
Has 1 Abyssal Socket
Has 1 Abyssal Socket
100% increased Effect of Socketed Abyss Jewels
			<ModRange range="0.5" id="1"/>
			<ModRange range="0.5" id="2"/>
			<ModRange range="0.5" id="3"/>
		</Item>
		<Item id="20">
			Rarity: RARE
Death Quill
Vile Arrow Quiver
Unique ID: ea2c4e77b931c10ecc7d3d32cc7d53e70a82a449b595c1d6fe6f27e9dbe160ba
Hunter Item
Item Level: 86
LevelReq: 68
Implicits: 1
Gain 15% of Physical Damage as Extra Chaos Damage
+25% to Damage over Time Multiplier with Attack Skills
+24% to Chaos Damage over Time Multiplier with Attack Skills
Adds 30 to 61 Chaos Damage to Attacks
+142 to maximum Life
49% increased Damage with Bow Skills
{crafted}12% increased Attack Speed
			<ModRange range="0.5" id="1"/>
			<ModRange range="0.5" id="2"/>
			<ModRange range="0.5" id="3"/>
			<ModRange range="0.5" id="4"/>
			<ModRange range="0.5" id="5"/>
			<ModRange range="0.5" id="6"/>
			<ModRange range="0.5" id="7"/>
		</Item>
		<Item id="21">
			Rarity: UNIQUE
Kalandra&apos;s Touch
Ring
Unique ID: 6072447d11ba8c08d97eeb823d06f230f42cc4951312a8eba617d6c875bd3879
Item Level: 83
Implicits: 0
Reflects your other Ring
			<ModRange range="0.5" id="1"/>
		</Item>
		<Item id="22">
			Rarity: MAGIC
Chemist&apos;s Quartz Flask of the Order
Unique ID: c7491e748d8fda02894a40dbb34fa52d0ce102d44ba20ea7342bfc5e5d8256f4
Item Level: 85
Quality: 20
LevelReq: 65
Implicits: 1
{crafted}Used when Charges reach full
28% reduced Charges per use
{crafted}Regenerate 3% of Life per second during Effect
			<ModRange range="0.5" id="4"/>
			<ModRange range="0.5" id="5"/>
		</Item>
		<Item id="23">
			Rarity: UNIQUE
The Utmost
Gold Amulet
Unique ID: b2b0e6d977062588fc9eb223bc84852a1988bbe172e44fa6476669e399cb76b8
Item Level: 87
LevelReq: 40
Implicits: 2
{crafted}Allocates Vigour
14% increased Rarity of Items found
+19% chance to Suppress Spell Damage
+6% to all maximum Elemental Resistances
32% increased Attack and Cast Speed
Damage Penetrates 10% Elemental Resistances
Corrupted
			<ModRange range="0.5" id="1"/>
			<ModRange range="0.5" id="2"/>
			<ModRange range="0.5" id="3"/>
			<ModRange range="0.5" id="4"/>
			<ModRange range="0.5" id="5"/>
			<ModRange range="0.5" id="6"/>
		</Item>
		<Item id="24">
			Rarity: MAGIC
Analyst&apos;s Quicksilver Flask of the Lynx
Unique ID: 9e3b86342d87cce92be61e9f98e3944ce299af93ca7223d1013ec24121ce656e
Item Level: 85
Quality: 20
LevelReq: 52
Implicits: 1
{crafted}Used when Charges reach full
24% increased Duration
10% increased Movement Speed during Effect
			<ModRange range="0.5" id="3"/>
			<ModRange range="0.5" id="4"/>
		</Item>
		<Item id="25">
			Rarity: MAGIC
Chemist&apos;s Granite Flask of the Tortoise
Unique ID: 87db7a7b402495894ba133a253936e6a9889bc5d6aaeefd90bfdf735adfb6027
Item Level: 84
Quality: 20
LevelReq: 65
Implicits: 1
{crafted}Used when Charges reach full
26% reduced Charges per use
49% increased Armour during Effect
			<ModRange range="0.5" id="3"/>
			<ModRange range="0.5" id="4"/>
		</Item>
		<Item id="26">
			Rarity: RARE
Phoenix Ward
Conquest Lamellar
Armour: 2844
ArmourBasePercentile: 0.9722
Evasion: 2882
EvasionBasePercentile: 0.9707
Unique ID: b197e25e3c23f197bebb60d49f96b7621a491bde092ebb318f83f29f6cbe663e
Item Level: 84
Quality: 20
Sockets: W-B-B-B-R-B
LevelReq: 84
Implicits: 2
11% of Physical Damage from Hits taken as Lightning Damage
+2% to all maximum Resistances
+357 to Armour
+373 to Evasion Rating
100% increased Armour and Evasion
+48% to Fire Resistance
+35% to Chaos Resistance
+1 to maximum number of Spectres
{crafted}+10% chance to Suppress Spell Damage
			<ModRange range="0.5" id="1"/>
			<ModRange range="0.5" id="2"/>
			<ModRange range="0.5" id="3"/>
			<ModRange range="0.5" id="4"/>
			<ModRange range="0.5" id="5"/>
			<ModRange range="0.5" id="6"/>
			<ModRange range="0.5" id="7"/>
			<ModRange range="0.5" id="8"/>
			<ModRange range="0.5" id="9"/>
		</Item>
		<Item id="27">
			Rarity: RARE
Phoenix March
Dragonscale Boots
Armour: 152
ArmourBasePercentile: 0.3148
Evasion: 152
EvasionBasePercentile: 0.3148
Unique ID: 7797599706e89ab98d0a13567ad25abd1bdf1e8ee19dbc4b4b277f02badbfa5d
Item Level: 85
Quality: 20
Sockets: B-B-R-R
LevelReq: 65
Implicits: 2
Regenerate 0.2% of Life per second per Endurance Charge
5% increased Action Speed
{fractured}+125 to maximum Life
+14% chance to Suppress Spell Damage
+47% to Lightning Resistance
+35% to Chaos Resistance
30% increased Movement Speed
100% chance to Avoid being Chilled
{crafted}100% chance to Avoid being Frozen
			<ModRange range="0.5" id="1"/>
			<ModRange range="0.5" id="2"/>
			<ModRange range="0.5" id="3"/>
			<ModRange range="0.5" id="4"/>
			<ModRange range="0.5" id="5"/>
			<ModRange range="0.5" id="6"/>
			<ModRange range="0.5" id="7"/>
			<ModRange range="0.5" id="8"/>
			<ModRange range="0.5" id="9"/>
		</Item>
		<Item id="28">
			Rarity: RARE
Honour Vise
Wyvernscale Gauntlets
Armour: 283
ArmourBasePercentile: 1
Evasion: 325
EvasionBasePercentile: 1
Unique ID: b9c40662222e75666c1b5f7cd7515d234c0a52330e50eb8102b407d18d024119
Item Level: 86
Quality: 20
Sockets: B B G G
LevelReq: 84
Implicits: 2
+10% chance to Suppress Spell Damage
While a Unique Enemy is in your Presence, Minions deal 34% increased Damage
{fractured}+128 to maximum Life
+12% chance to Suppress Spell Damage
+35 to Evasion Rating
+24 to maximum Life
+46% to Cold Resistance
+25% to Chaos Resistance
{crafted}Minions deal 20% increased Damage
			<ModRange range="0.5" id="1"/>
			<ModRange range="0.5" id="2"/>
			<ModRange range="0.5" id="3"/>
			<ModRange range="0.5" id="4"/>
			<ModRange range="0.5" id="5"/>
			<ModRange range="0.5" id="6"/>
			<ModRange range="0.5" id="7"/>
			<ModRange range="0.5" id="8"/>
			<ModRange range="0.5" id="9"/>
		</Item>
		<Item id="29">
			Rarity: UNIQUE
Widowhail
Crude Bow
Unique ID: 10c1f44d6d2a434e6b9638ed89a7fdd1bfc8809119c27a3af9d0abbc1a94e245
Item Level: 82
Quality: 17
Sockets: G-B-B-B-G-G
Implicits: 4
{crafted}Quality does not increase Physical Damage
{crafted}1% increased Attack Speed per 8% Quality
Socketed Gems are Supported by Level 10 Momentum
4% increased Attack Speed
247% increased bonuses gained from Equipped Quiver
Corrupted
			<ModRange range="0.5" id="1"/>
			<ModRange range="0.5" id="2"/>
			<ModRange range="0.5" id="3"/>
			<ModRange range="0.5" id="4"/>
			<ModRange range="0.5" id="5"/>
		</Item>
		<Item id="30">
			Rarity: UNIQUE
Progenesis
Amethyst Flask
Unique ID: f440511d1821c180ac433685169bb972b73f202c7961031452ad3839c1c12f78
Item Level: 87
Quality: 20
LevelReq: 60
Implicits: 1
{crafted}Used when Charges reach full
15% reduced Charges per use
10% increased Duration
When Hit during effect, 25% of Life loss from Damage taken occurs over 4 seconds instead
			<ModRange range="0.5" id="3"/>
			<ModRange range="0.5" id="4"/>
			<ModRange range="0.5" id="5"/>
		</Item>
		<Item id="31">
			Rarity: RARE
Demon Loop
Bone Ring
Unique ID: 305528d3ca8bc78f11aa61a5abe98c9bfa6f24f16b593cd1d5385334d738cdee
Item Level: 85
LevelReq: 64
Implicits: 1
9% increased maximum Life
+135 to maximum Life
Minions have 37% increased maximum Life
Minions deal 36% increased Damage
Minions have +15% to all Elemental Resistances
Minions have 12% increased Attack and Cast Speed
{crafted}Regenerate 30 Life per second
{crafted}+52 to maximum Mana
			<ModRange range="0.5" id="1"/>
			<ModRange range="0.5" id="2"/>
			<ModRange range="0.5" id="3"/>
			<ModRange range="0.5" id="4"/>
			<ModRange range="0.5" id="5"/>
			<ModRange range="0.5" id="6"/>
			<ModRange range="0.5" id="7"/>
			<ModRange range="0.5" id="8"/>
		</Item>
		<Item variant="2" id="32">
			Rarity: UNIQUE
Crown of the Tyrant
Magistrate Crown
Armour: 227
ArmourBasePercentile: 1
Energy Shield: 47
EnergyShieldBasePercentile: 1
League: Delve
Variant: Pre 3.11.0
Variant: Current
Selected Variant: 2
Quality: 20
Sockets: W
LevelReq: 58
Implicits: 0
Has 1 Socket
{variant:1}{range:0.5}+(50-100) to maximum Life
{variant:2}{range:0.5}+(50-175) to maximum Life
Nearby Enemies have -10% to all Resistances
You and Nearby Allies have 64 to 96 added Fire Damage per Red Socket
You and Nearby Allies have 56 to 88 added Cold Damage per Green Socket
You and Nearby Allies have 16 to 144 added Lightning Damage per Blue Socket
You and Nearby Allies have 47 to 61 added Chaos Damage per White Socket
			<ModRange range="0.5" id="1"/>
			<ModRange range="0.5" id="2"/>
			<ModRange range="0.5" id="3"/>
			<ModRange range="0.5" id="4"/>
			<ModRange range="0.5" id="5"/>
			<ModRange range="0.5" id="6"/>
			<ModRange range="0.5" id="7"/>
			<ModRange range="0.5" id="8"/>
		</Item>
		<Item variant="6" id="33">
			Rarity: UNIQUE
Kingmaker
Despot Axe
Variant: Pre 2.6.0
Variant: Pre 3.6.0
Variant: Pre 3.11.0
Variant: Pre 3.16.0
Variant: Pre 3.20.0
Variant: Current
Selected Variant: 6
Quality: 20
Sockets: R-R-R-R-R-R
LevelReq: 66
Implicits: 0
{variant:1,2}{range:0.5}(200-250)% increased Physical Damage
{variant:3}{range:0.5}(250-285)% increased Physical Damage
{variant:4}{range:0.5}(170-200)% increased Physical Damage
{variant:5}{range:0.5}(190-240)% increased Physical Damage
{variant:6}{range:0.5}(300-360)% increased Physical Damage
{range:0.5}(7-12)% increased Attack Speed
{variant:2,3,4,5,6}{range:0.5}(30-40)% increased Critical Strike Chance
{variant:1}{range:0.5}+(100-150) to maximum Mana
Nearby Allies have 30% increased Item Rarity
Nearby Allies have Culling Strike
{variant:2,3,4,5,6}Insufficient Mana doesn&apos;t prevent your Melee Attacks
{variant:3,4,5,6}Nearby Allies have +50% to Critical Strike Multiplier
{variant:3,4}Nearby Allies have +1 Fortification
{variant:5,6}Nearby Allies have +10 Fortification
			<ModRange range="0.5" id="1"/>
			<ModRange range="0.5" id="2"/>
			<ModRange range="0.5" id="3"/>
			<ModRange range="0.5" id="4"/>
			<ModRange range="0.5" id="5"/>
			<ModRange range="0.5" id="6"/>
			<ModRange range="0.5" id="7"/>
			<ModRange range="0.5" id="8"/>
			<ModRange range="0.5" id="9"/>
			<ModRange range="0.5" id="10"/>
			<ModRange range="0.5" id="12"/>
			<ModRange range="0.5" id="13"/>
			<ModRange range="0.5" id="14"/>
		</Item>
		<Item id="34">
			Rarity: UNIQUE
Garb of the Ephemeral
Savant&apos;s Robe
Energy Shield: 483
EnergyShieldBasePercentile: 1
League: Synthesis
Quality: 20
Sockets: B-B-B-B-B-B
LevelReq: 56
Implicits: 0
{fractured}{range:0.5}(180-230)% increased Energy Shield
+600 Strength and Intelligence Requirement
Gain a Divine Charge on Hit
+10 to maximum Divine Charges
You gain Divinity for 10 seconds on reaching maximum Divine Charges
Lose all Divine Charges when you gain Divinity
Nearby Allies&apos; Action Speed cannot be modified to below base value
Nearby Enemies cannot deal Critical Strikes
			<ModRange range="0.5" id="1"/>
			<ModRange range="0.5" id="2"/>
			<ModRange range="0.5" id="4"/>
			<ModRange range="0.5" id="5"/>
			<ModRange range="0.5" id="7"/>
			<ModRange range="0.5" id="8"/>
		</Item>
		<Item variant="3" id="35">
			Rarity: UNIQUE
Asenath&apos;s Gentle Touch
Silk Gloves
Energy Shield: 28
EnergyShieldBasePercentile: 1
League: Legion
Variant: Pre 2.6.0
Variant: Pre 3.7.0
Variant: Current
Selected Variant: 3
Quality: 20
Sockets: B-B-B-B
LevelReq: 25
Implicits: 0
{range:0.5}+(20-30) to Intelligence
{variant:1,2}{range:0.5}+(20-30) to maximum Life
{variant:3}{range:0.5}+(60-80) to maximum Life
{variant:1,2}{range:0.5}+(20-30) to maximum Mana
{variant:3}{range:0.5}+(60-80) to maximum Mana
{variant:1,2,3}Curse Enemies with Temporal Chains on Hit
{variant:3}Non-Aura Curses you inflict are not removed from Dying Enemies
{variant:3}Enemies near Corpses affected by your Curses are Blinded
{variant:3}Enemies killed near Corpses affected by your Curses explode, dealing
3% of their Life as Physical Damage
			<ModRange range="0.5" id="1"/>
			<ModRange range="0.5" id="2"/>
			<ModRange range="0.5" id="3"/>
			<ModRange range="0.5" id="4"/>
			<ModRange range="0.5" id="5"/>
			<ModRange range="0.5" id="6"/>
			<ModRange range="0.5" id="8"/>
			<ModRange range="0.5" id="9"/>
		</Item>
		<Item variant="3" id="36">
			Rarity: UNIQUE
Windscream
Reinforced Greaves
Armour: 238
ArmourBasePercentile: 1
Variant: Pre 2.6.0
Variant: Pre 3.19.0
Variant: Current
Selected Variant: 3
Quality: 20
Sockets: R-R-R-R
LevelReq: 33
Implicits: 0
{range:0.5}(50-80)% increased Armour
{range:0.5}+(10-15)% to all Elemental Resistances
{variant:1}10% increased Movement Speed
{variant:2}15% increased Movement Speed
{variant:3}20% increased Movement Speed
{variant:1}10% increased Elemental Damage
{variant:2}{range:0.5}(10-20)% increased Elemental Damage
You can apply an additional Curse
{variant:3}50% increased Area of Effect of Hex Skills
			<ModRange range="0.5" id="1"/>
			<ModRange range="0.5" id="2"/>
			<ModRange range="0.5" id="3"/>
			<ModRange range="0.5" id="4"/>
			<ModRange range="0.5" id="5"/>
			<ModRange range="0.5" id="6"/>
			<ModRange range="0.5" id="7"/>
			<ModRange range="0.5" id="8"/>
			<ModRange range="0.5" id="9"/>
		</Item>
		<ItemSet useSecondWeaponSet="false" id="1">
			<Slot itemPbURL="" name="Gloves" itemId="28"/>
			<Slot itemPbURL="" name="Weapon 1" itemId="29"/>
			<Slot itemPbURL="" name="Boots Abyssal Socket 5" itemId="0"/>
			<SocketIdURL nodeId="26196" name="Jewel 26196" itemPbURL=""/>
			<Slot itemPbURL="" name="Belt Abyssal Socket 2" itemId="18"/>
			<Slot itemPbURL="" name="Flask 3" itemId="25"/>
			<Slot itemPbURL="" name="Weapon 1 Swap Abyssal Socket 4" itemId="0"/>
			<Slot itemPbURL="" name="Weapon 1 Abyssal Socket 5" itemId="0"/>
			<Slot itemPbURL="" name="Weapon 2 Abyssal Socket 5" itemId="0"/>
			<Slot itemPbURL="" name="Weapon 1 Swap Abyssal Socket 6" itemId="0"/>
			<Slot itemPbURL="" name="Weapon 1 Abyssal Socket 6" itemId="0"/>
			<Slot itemPbURL="" name="Weapon 2 Abyssal Socket 6" itemId="0"/>
			<Slot itemPbURL="" name="Weapon 2 Swap Abyssal Socket 1" itemId="0"/>
			<SocketIdURL nodeId="23756" name="Jewel 23756" itemPbURL=""/>
			<SocketIdURL nodeId="31683" name="Jewel 31683" itemPbURL=""/>
			<Slot itemPbURL="" name="Boots Abyssal Socket 3" itemId="0"/>
			<Slot itemPbURL="" name="Weapon 1 Abyssal Socket 2" itemId="0"/>
			<Slot itemPbURL="" name="Weapon 2 Swap Abyssal Socket 4" itemId="0"/>
			<Slot itemPbURL="" name="Helmet Abyssal Socket 1" itemId="0"/>
			<Slot itemPbURL="" name="Belt Abyssal Socket 6" itemId="0"/>
			<Slot itemPbURL="" name="Helmet Abyssal Socket 2" itemId="0"/>
			<Slot itemPbURL="" name="Helmet" itemId="16"/>
			<Slot itemPbURL="" name="Helmet Abyssal Socket 3" itemId="0"/>
			<Slot itemPbURL="" name="Weapon 2 Swap Abyssal Socket 5" itemId="0"/>
			<Slot itemPbURL="" name="Weapon 1 Abyssal Socket 1" itemId="0"/>
			<Slot itemPbURL="" name="Weapon 2 Abyssal Socket 1" itemId="0"/>
			<Slot itemPbURL="" name="Weapon 1 Abyssal Socket 4" itemId="0"/>
			<Slot itemPbURL="" name="Belt" itemId="19"/>
			<Slot itemPbURL="" name="Weapon 1 Swap Abyssal Socket 2" itemId="0"/>
			<Slot itemPbURL="" name="Boots Abyssal Socket 4" itemId="0"/>
			<Slot itemPbURL="" name="Weapon 2 Abyssal Socket 2" itemId="0"/>
			<Slot itemPbURL="" name="Flask 5" itemId="30"/>
			<SocketIdURL nodeId="55190" name="Jewel 55190" itemPbURL=""/>
			<Slot itemPbURL="" name="Weapon 1 Swap Abyssal Socket 3" itemId="0"/>
			<Slot itemPbURL="" name="Boots Abyssal Socket 2" itemId="0"/>
			<Slot itemPbURL="" name="Belt Abyssal Socket 3" itemId="0"/>
			<Slot itemPbURL="" name="Body Armour Abyssal Socket 1" itemId="0"/>
			<Slot itemPbURL="" name="Gloves Abyssal Socket 1" itemId="0"/>
			<SocketIdURL nodeId="46519" name="Jewel 46519" itemPbURL=""/>
			<Slot itemPbURL="" name="Helmet Abyssal Socket 5" itemId="0"/>
			<Slot itemPbURL="" name="Helmet Abyssal Socket 6" itemId="0"/>
			<SocketIdURL nodeId="44169" name="Jewel 44169" itemPbURL=""/>
			<SocketIdURL nodeId="33631" name="Jewel 33631" itemPbURL=""/>
			<Slot itemPbURL="" name="Weapon 1 Swap Abyssal Socket 1" itemId="0"/>
			<Slot itemPbURL="" name="Weapon 2 Swap Abyssal Socket 2" itemId="0"/>
			<SocketIdURL nodeId="2491" name="Jewel 2491" itemPbURL=""/>
			<SocketIdURL nodeId="34483" name="Jewel 34483" itemPbURL=""/>
			<Slot itemPbURL="" name="Flask 1" itemId="15"/>
			<SocketIdURL nodeId="28475" name="Jewel 28475" itemPbURL=""/>
			<Slot itemPbURL="" name="Helmet Abyssal Socket 4" itemId="0"/>
			<Slot itemPbURL="" name="Gloves Abyssal Socket 5" itemId="0"/>
			<Slot itemPbURL="" name="Body Armour Abyssal Socket 2" itemId="0"/>
			<Slot itemPbURL="" name="Amulet" itemId="23"/>
			<Slot itemPbURL="" name="Weapon 1 Abyssal Socket 3" itemId="0"/>
			<Slot itemPbURL="" name="Weapon 2 Abyssal Socket 3" itemId="0"/>
			<SocketIdURL nodeId="36634" name="Jewel 36634" itemPbURL=""/>
			<Slot itemPbURL="" name="Belt Abyssal Socket 4" itemId="0"/>
			<SocketIdURL nodeId="10532" name="Jewel 10532" itemPbURL=""/>
			<Slot itemPbURL="" name="Belt Abyssal Socket 1" itemId="17"/>
			<Slot itemPbURL="" name="Body Armour Abyssal Socket 3" itemId="0"/>
			<Slot itemPbURL="" name="Weapon 2 Swap" itemId="0"/>
			<Slot itemPbURL="" name="Flask 4" itemId="22"/>
			<Slot itemPbURL="" name="Flask 2" itemId="24"/>
			<Slot itemPbURL="" name="Weapon 2" itemId="20"/>
			<Slot itemPbURL="" name="Belt Abyssal Socket 5" itemId="0"/>
			<Slot itemPbURL="" name="Boots Abyssal Socket 1" itemId="0"/>
			<Slot itemPbURL="" name="Body Armour Abyssal Socket 4" itemId="0"/>
			<Slot itemPbURL="" name="Weapon 2 Swap Abyssal Socket 6" itemId="0"/>
			<Slot itemPbURL="" name="Weapon 2 Swap Abyssal Socket 3" itemId="0"/>
			<Slot itemPbURL="" name="Weapon 1 Swap" itemId="0"/>
			<Slot itemPbURL="" name="Ring 2" itemId="31"/>
			<Slot itemPbURL="" name="Gloves Abyssal Socket 2" itemId="0"/>
			<SocketIdURL nodeId="49080" name="Jewel 49080" itemPbURL=""/>
			<SocketIdURL nodeId="26725" name="Jewel 26725" itemPbURL=""/>
			<Slot itemPbURL="" name="Body Armour Abyssal Socket 6" itemId="0"/>
			<Slot itemPbURL="" name="Weapon 1 Swap Abyssal Socket 5" itemId="0"/>
			<Slot itemPbURL="" name="Weapon 2 Abyssal Socket 4" itemId="0"/>
			<Slot itemPbURL="" name="Body Armour" itemId="26"/>
			<Slot itemPbURL="" name="Ring 1" itemId="21"/>
			<Slot itemPbURL="" name="Gloves Abyssal Socket 3" itemId="0"/>
			<Slot itemPbURL="" name="Body Armour Abyssal Socket 5" itemId="0"/>
			<Slot itemPbURL="" name="Gloves Abyssal Socket 4" itemId="0"/>
			<Slot itemPbURL="" name="Gloves Abyssal Socket 6" itemId="0"/>
			<Slot itemPbURL="" name="Boots" itemId="27"/>
			<Slot itemPbURL="" name="Boots Abyssal Socket 6" itemId="0"/>
		</ItemSet>
		<ItemSet useSecondWeaponSet="false" title="AG" id="2">
			<Slot itemPbURL="" name="Gloves" itemId="35"/>
			<Slot itemPbURL="" name="Weapon 1" itemId="33"/>
			<Slot itemPbURL="" name="Boots Abyssal Socket 5" itemId="0"/>
			<SocketIdURL nodeId="26196" name="Jewel 26196" itemPbURL=""/>
			<Slot itemPbURL="" name="Belt Abyssal Socket 2" itemId="0"/>
			<Slot itemPbURL="" name="Flask 3" itemId="0"/>
			<Slot itemPbURL="" name="Weapon 1 Swap Abyssal Socket 4" itemId="0"/>
			<Slot itemPbURL="" name="Weapon 1 Abyssal Socket 5" itemId="0"/>
			<Slot itemPbURL="" name="Weapon 2 Abyssal Socket 5" itemId="0"/>
			<Slot itemPbURL="" name="Weapon 1 Swap Abyssal Socket 6" itemId="0"/>
			<Slot itemPbURL="" name="Weapon 1 Abyssal Socket 6" itemId="0"/>
			<Slot itemPbURL="" name="Weapon 2 Abyssal Socket 6" itemId="0"/>
			<Slot itemPbURL="" name="Weapon 2 Swap Abyssal Socket 1" itemId="0"/>
			<SocketIdURL nodeId="23756" name="Jewel 23756" itemPbURL=""/>
			<SocketIdURL nodeId="31683" name="Jewel 31683" itemPbURL=""/>
			<Slot itemPbURL="" name="Boots Abyssal Socket 3" itemId="0"/>
			<Slot itemPbURL="" name="Weapon 1 Abyssal Socket 2" itemId="0"/>
			<Slot itemPbURL="" name="Weapon 2 Swap Abyssal Socket 4" itemId="0"/>
			<Slot itemPbURL="" name="Helmet Abyssal Socket 1" itemId="0"/>
			<Slot itemPbURL="" name="Belt Abyssal Socket 6" itemId="0"/>
			<Slot itemPbURL="" name="Helmet Abyssal Socket 2" itemId="0"/>
			<Slot itemPbURL="" name="Helmet" itemId="32"/>
			<Slot itemPbURL="" name="Helmet Abyssal Socket 3" itemId="0"/>
			<Slot itemPbURL="" name="Weapon 2 Swap Abyssal Socket 5" itemId="0"/>
			<Slot itemPbURL="" name="Weapon 1 Abyssal Socket 1" itemId="0"/>
			<Slot itemPbURL="" name="Weapon 2 Abyssal Socket 1" itemId="0"/>
			<Slot itemPbURL="" name="Weapon 1 Abyssal Socket 4" itemId="0"/>
			<Slot itemPbURL="" name="Belt" itemId="0"/>
			<Slot itemPbURL="" name="Weapon 1 Swap Abyssal Socket 2" itemId="0"/>
			<Slot itemPbURL="" name="Boots Abyssal Socket 4" itemId="0"/>
			<Slot itemPbURL="" name="Weapon 2 Abyssal Socket 2" itemId="0"/>
			<Slot itemPbURL="" name="Flask 5" itemId="0"/>
			<SocketIdURL nodeId="55190" name="Jewel 55190" itemPbURL=""/>
			<Slot itemPbURL="" name="Weapon 1 Swap Abyssal Socket 3" itemId="0"/>
			<Slot itemPbURL="" name="Boots Abyssal Socket 2" itemId="0"/>
			<Slot itemPbURL="" name="Belt Abyssal Socket 3" itemId="0"/>
			<Slot itemPbURL="" name="Body Armour Abyssal Socket 1" itemId="0"/>
			<Slot itemPbURL="" name="Gloves Abyssal Socket 1" itemId="0"/>
			<SocketIdURL nodeId="46519" name="Jewel 46519" itemPbURL=""/>
			<Slot itemPbURL="" name="Helmet Abyssal Socket 5" itemId="0"/>
			<Slot itemPbURL="" name="Helmet Abyssal Socket 6" itemId="0"/>
			<SocketIdURL nodeId="44169" name="Jewel 44169" itemPbURL=""/>
			<SocketIdURL nodeId="33631" name="Jewel 33631" itemPbURL=""/>
			<Slot itemPbURL="" name="Weapon 1 Swap Abyssal Socket 1" itemId="0"/>
			<Slot itemPbURL="" name="Weapon 2 Swap Abyssal Socket 2" itemId="0"/>
			<SocketIdURL nodeId="2491" name="Jewel 2491" itemPbURL=""/>
			<SocketIdURL nodeId="34483" name="Jewel 34483" itemPbURL=""/>
			<Slot itemPbURL="" name="Flask 1" itemId="0"/>
			<SocketIdURL nodeId="28475" name="Jewel 28475" itemPbURL=""/>
			<Slot itemPbURL="" name="Helmet Abyssal Socket 4" itemId="0"/>
			<Slot itemPbURL="" name="Gloves Abyssal Socket 5" itemId="0"/>
			<Slot itemPbURL="" name="Body Armour Abyssal Socket 2" itemId="0"/>
			<Slot itemPbURL="" name="Amulet" itemId="0"/>
			<Slot itemPbURL="" name="Weapon 1 Abyssal Socket 3" itemId="0"/>
			<Slot itemPbURL="" name="Weapon 2 Abyssal Socket 3" itemId="0"/>
			<SocketIdURL nodeId="36634" name="Jewel 36634" itemPbURL=""/>
			<Slot itemPbURL="" name="Belt Abyssal Socket 4" itemId="0"/>
			<SocketIdURL nodeId="10532" name="Jewel 10532" itemPbURL=""/>
			<Slot itemPbURL="" name="Belt Abyssal Socket 1" itemId="0"/>
			<Slot itemPbURL="" name="Body Armour Abyssal Socket 3" itemId="0"/>
			<Slot itemPbURL="" name="Weapon 2 Swap" itemId="0"/>
			<Slot itemPbURL="" name="Flask 4" itemId="0"/>
			<Slot itemPbURL="" name="Flask 2" itemId="0"/>
			<Slot itemPbURL="" name="Weapon 2" itemId="0"/>
			<Slot itemPbURL="" name="Belt Abyssal Socket 5" itemId="0"/>
			<Slot itemPbURL="" name="Boots Abyssal Socket 1" itemId="0"/>
			<Slot itemPbURL="" name="Body Armour Abyssal Socket 4" itemId="0"/>
			<Slot itemPbURL="" name="Weapon 2 Swap Abyssal Socket 6" itemId="0"/>
			<Slot itemPbURL="" name="Weapon 2 Swap Abyssal Socket 3" itemId="0"/>
			<Slot itemPbURL="" name="Weapon 1 Swap" itemId="0"/>
			<Slot itemPbURL="" name="Ring 2" itemId="0"/>
			<Slot itemPbURL="" name="Gloves Abyssal Socket 2" itemId="0"/>
			<SocketIdURL nodeId="49080" name="Jewel 49080" itemPbURL=""/>
			<SocketIdURL nodeId="26725" name="Jewel 26725" itemPbURL=""/>
			<Slot itemPbURL="" name="Body Armour Abyssal Socket 6" itemId="0"/>
			<Slot itemPbURL="" name="Weapon 1 Swap Abyssal Socket 5" itemId="0"/>
			<Slot itemPbURL="" name="Weapon 2 Abyssal Socket 4" itemId="0"/>
			<Slot itemPbURL="" name="Body Armour" itemId="34"/>
			<Slot itemPbURL="" name="Ring 1" itemId="0"/>
			<Slot itemPbURL="" name="Gloves Abyssal Socket 3" itemId="0"/>
			<Slot itemPbURL="" name="Body Armour Abyssal Socket 5" itemId="0"/>
			<Slot itemPbURL="" name="Gloves Abyssal Socket 4" itemId="0"/>
			<Slot itemPbURL="" name="Gloves Abyssal Socket 6" itemId="0"/>
			<Slot itemPbURL="" name="Boots" itemId="36"/>
			<Slot itemPbURL="" name="Boots Abyssal Socket 6" itemId="0"/>
		</ItemSet>
		<TradeSearchWeights/>
	</Items>
	<Config activeConfigSet="1">
		<ConfigSet title="Default" id="1">
			<Input name="conditionOnConsecratedGround" boolean="true"/>
			<Input name="feedingFrenzyFeedingFrenzyActive" boolean="true"/>
			<Input name="multiplierWitheredStackCount" number="15"/>
			<Input name="buffFortification" boolean="true"/>
			<Input name="conditionBeenHitRecently" boolean="true"/>
			<Input name="customMods" string="^5- Minion Taunt (Meatshield) -
Nearby Enemies deal 10% less damage

^4- AG Gear -
- Kingmaker -
Minions have +50% to Critical Strike Multiplier
Nearby Allies have Culling Strike

- Windscream Boots -
You can apply an additional Curse

- Asenath -
Curse Enemies with Temporal Chains on Hit

- Crown of the Tyrant + with White Socket -
Nearby Enemies have -10% to all Resistances
You and Nearby Allies have 47 to 61 added Chaos Damage

- Garb of the Ephemeral -
Nearby Enemies cannot deal Critical Strikes


------------------------

^4^1- Spectre Buffs -

^6- Spectral Leader -
You and Nearby Allies have 20% more attack and cast speed
^2
- Perfect Forest Tiger -
You and nearby allies gain 13% increased Movement Speed
You and nearby allies gain 19% increased Attack Speed
You and nearby allies gain 19% increased Cast Speed

^6- Perfect Forest Warrior -
Onslaugt (enabled via Config)

- Perfect Guardian Turtle -
Determination (enabled via Spectre menu)"/>
			<Input name="multiplierNearbyCorpse" number="5"/>
			<Input name="pantheonMajorGod" string="Lunaris"/>
			<Input name="buffOnslaught" boolean="true"/>
			<Input name="multiplierSummonedMinion" number="9"/>
			<Input name="deathmarkDeathmarkActive" boolean="true"/>
			<Input name="minionBuffOnslaught" boolean="true"/>
			<Input name="multiplierNearbyEnemies" number="1"/>
			<Input name="pantheonMinorGod" string="Ryslatha"/>
			<Input name="raiseSpectreEnableCurses" boolean="false"/>
			<Input name="overrideFortification" number="10"/>
			<Placeholder name="enemySpeed" number="700"/>
			<Placeholder name="enemyChaosResist" number="30"/>
			<Placeholder name="enemyLightningDamage" number="2241"/>
			<Placeholder name="enemyCritChance" number="5"/>
			<Placeholder name="enemyFireResist" number="50"/>
			<Placeholder name="enemyColdDamage" number="2241"/>
			<Placeholder name="enemyFireDamage" number="2241"/>
			<Placeholder name="enemyLevel" number="84"/>
			<Placeholder name="multiplierWitheredStackCountSelf" number="15"/>
			<Placeholder name="enemyColdResist" number="50"/>
			<Placeholder name="enemyLightningPen" number="3"/>
			<Placeholder name="enemyLightningResist" number="50"/>
			<Placeholder name="enemyChaosDamage" number="896"/>
			<Placeholder name="enemyEvasion" number="10143"/>
			<Placeholder name="enemyCritDamage" number="30"/>
			<Placeholder name="enemyColdPen" number="3"/>
			<Placeholder name="ScorchStacks" number="1"/>
			<Placeholder name="enemyDamageRollRange" number="70"/>
			<Placeholder name="enemyArmour" number="61989"/>
			<Placeholder name="sigilOfPowerStages" number="1"/>
			<Placeholder name="enemyPhysicalDamage" number="2241"/>
			<Placeholder name="enemyFirePen" number="3"/>
			<Placeholder name="ShockStacks" number="1"/>
		</ConfigSet>
	</Config>
</PathOfBuilding>
